MANIFEST.in
README.txt
setup.cfg
setup.py
docs/Makefile
docs/epydoc.conf.cfg
docs/source/conf.py
docs/source/_static/receptacle_logo.png
receptacle/__init__.py
receptacle/application.py
receptacle/architecture.py
receptacle/config.py
receptacle/debugging.py
receptacle/encoding.py
receptacle/network.py
receptacle/packaging.py
receptacle/runtime.py
receptacle/security.py
receptacle/server.py
receptacle/storage.py
receptacle.egg-info/PKG-INFO
receptacle.egg-info/SOURCES.txt
receptacle.egg-info/dependency_links.txt
receptacle.egg-info/top_level.txt
receptacle/bus/__init__.py
receptacle/bus/services.py
receptacle/bus/spline.py
receptacle/bus/partners/__init__.py
receptacle/bus/partners/adhoc.py
receptacle/bus/partners/cluster.py
receptacle/bus/partners/main.py
receptacle/client/__init__.py
receptacle/client/cli.py
receptacle/client/support.py
receptacle/servicelib/__init__.py
receptacle/servicelib/cron.py
receptacle/servicelib/docmgr.py
receptacle/servicelib/registry.py
receptacle/servicelib/web/__init__.py
receptacle/servicelib/web/falcon/__init__.py
receptacle/servicelib/web/falcon/manage.py
receptacle/servicelib/web/falcon/settings.py
receptacle/servicelib/web/falcon/urls.py
receptacle/servicelib/web/falcon/views.py
receptacle/servicelib/web/falcon/media/css/status.css
receptacle/servicelib/web/falcon/media/images/action.png
receptacle/servicelib/web/falcon/media/images/favicon.ico
receptacle/servicelib/web/falcon/media/images/point.png
receptacle/servicelib/web/falcon/media/images/receptacle_bg.png
receptacle/servicelib/web/falcon/media/js/status.js
receptacle/servicelib/web/falcon/templates/page_base.html
receptacle/servicelib/web/falcon/templates/status.html
scripts/notemgr.py
scripts/receptacleCmd
scripts/registry-connect
scripts/registry-shutdown
scripts/registry.env
scripts/run-registry.sh
scripts/spline-shutdown
scripts/spline.cfg
scripts/spline.sh
scripts/user-login
scripts/partners/projects-repos.ptr
scripts/partners/registry.ptr
scripts/partners/skype-terminal.ptr
scripts/partners/stuphmud-autorun.ptr
scripts/partners/stuphmud.ptr
scripts/partners/web-facing.ptr
